Metadata-Version: 1.0
Name: bino-dag-prob
Version: 1.0
Summary: Binomial and Gaussian distributions
Home-page: UNKNOWN
Author: UNKNOWN
Author-email: UNKNOWN
License: UNKNOWN
Platform: UNKNOWN
